barbell2/__init__.py
barbell2/common.py
barbell2/utils.py
barbell2/bodycomp/__init__.py
barbell2/bodycomp/adddcmext.py
barbell2/bodycomp/calculator.py
barbell2/bodycomp/createh5.py
barbell2/bodycomp/decompdcm.py
barbell2/bodycomp/filterdcm.py
barbell2/bodycomp/flattendirs.py
barbell2/bodycomp/seg.py
barbell2/bodycomp/selectroi.py
barbell2/bodycomp/selectslice.py
barbell2/bodycomp/totalseg.py
barbell2/castor/__init__.py
barbell2/castor/api.py
barbell2/castor/builders.py
barbell2/castor/buildimport.py
barbell2/castor/castor2sqlite.py
barbell2/castor/data.py
barbell2/castor/loaders.py
barbell2/converters/__init__.py
barbell2/converters/dcm2nifti.py
barbell2/converters/dcm2npy.py
barbell2/converters/npy2dcm.py
barbell2/converters/npy2nrrd.py
barbell2/converters/npy2png.py
barbell2/converters/tag2dcm.py
barbell2/converters/tag2npy.py
barbell2-2.63.0.dist-info/LICENSE
barbell2-2.63.0.dist-info/METADATA
barbell2-2.63.0.dist-info/WHEEL
barbell2-2.63.0.dist-info/entry_points.txt
barbell2-2.63.0.dist-info/top_level.txt
barbell2-2.63.0.dist-info/RECORD
