Metadata-Version: 2.1
Name: barbell2
Version: 2.63.0
Summary: Collection of Python libraries and tools
Home-page: https://github.com/rbrecheisen/barbell2
Author: Ralph Brecheisen
Author-email: ralph.brecheisen@gmail.com
License: MIT license
Keywords: barbell2
Platform: UNKNOWN
Classifier: Development Status :: 2 - Pre-Alpha
Classifier: Intended Audience :: Developers
Classifier: License :: OSI Approved :: MIT License
Classifier: Natural Language :: English
Classifier: Programming Language :: Python :: 3
Classifier: Programming Language :: Python :: 3.5
Classifier: Programming Language :: Python :: 3.6
Classifier: Programming Language :: Python :: 3.7
Classifier: Programming Language :: Python :: 3.8
Requires-Python: >=3.5
Requires-Dist: pydicom
Requires-Dist: numpy
Requires-Dist: matplotlib
Requires-Dist: pandas
Requires-Dist: openpyxl
Requires-Dist: nibabel
Requires-Dist: pyside6
Requires-Dist: pyopengl
Requires-Dist: pygame
Requires-Dist: PyInstaller
Requires-Dist: pynrrd
Requires-Dist: oauthlib
Requires-Dist: requests-oauthlib
